cmip7_data_request_api-1.4.dist-info/licenses/LICENSE
data_request_api/__init__.py
data_request_api/version.py
data_request_api/command_line/__init__.py
data_request_api/command_line/compare_variables.py
data_request_api/command_line/config.py
data_request_api/command_line/estimate_dreq_volume.py
data_request_api/command_line/export_dreq_lists_json.py
data_request_api/command_line/get_variables_metadata.py
data_request_api/content/README.MD
data_request_api/content/__init__.py
data_request_api/content/consolidate_export.py
data_request_api/content/dreq_content.py
data_request_api/content/dump_transformation.py
data_request_api/content/mapping_table.py
data_request_api/content/transform.json
data_request_api/content/utils.py
data_request_api/query/__init__.py
data_request_api/query/data_request.py
data_request_api/query/dreq_classes.py
data_request_api/query/dreq_query.py
data_request_api/query/filtering.json
data_request_api/query/vocabulary_server.py
data_request_api/tests/__init__.py
data_request_api/tests/test_cli.py
data_request_api/tests/test_config.py
data_request_api/tests/test_config_cli.py
data_request_api/tests/test_consolidation.py
data_request_api/tests/test_data_request.py
data_request_api/tests/test_decorator.py
data_request_api/tests/test_dreq_content.py
data_request_api/tests/test_dreq_query.py
data_request_api/tests/test_dump_transformation.py
data_request_api/tests/test_optimize.py
data_request_api/tests/test_vocabulary_server.py
data_request_api/tests/test_datasets/DR_raw_not-consolidate_content.json
data_request_api/tests/test_datasets/DR_release_not-consolidate_content.json
data_request_api/tests/test_datasets/DR_release_not-consolidate_content_dump.txt
data_request_api/tests/test_datasets/VS_raw_not-consolidate_content.json
data_request_api/tests/test_datasets/VS_release_not-consolidate_content.json
data_request_api/tests/test_datasets/dreq_raw_export.json
data_request_api/tests/test_datasets/dreq_release_export.json
data_request_api/tests/test_datasets/raw_not-consolidate_output_format.json
cmip7_data_request_api-1.4.dist-info/METADATA
cmip7_data_request_api-1.4.dist-info/WHEEL
cmip7_data_request_api-1.4.dist-info/entry_points.txt
cmip7_data_request_api-1.4.dist-info/top_level.txt
cmip7_data_request_api-1.4.dist-info/RECORD
