Metadata-Version: 2.4
Name: CMIP7_data_request_api
Version: 1.4
Summary: A programmatic interface to the CMIP7 Data Request
Author: James Anstey, Gaëlle Rigoudy, Martin Schupfner, Matthew Mizielinski, Daniel Ellis, Elisabeth Dingley, Marie-Pierre Moine
License: MIT License
Project-URL: Homepage, https://github.com/CMIP-Data-Request/CMIP7_DReq_Software
Project-URL: Issues, https://github.com/CMIP-Data-Request/CMIP7_DReq_Software/issues
Classifier: Programming Language :: Python :: 3
Classifier: Operating System :: OS Independent
Requires-Python: >=3.8
License-File: LICENSE
Requires-Dist: pooch
Requires-Dist: openpyxl
Requires-Dist: requests
Requires-Dist: beautifulsoup4
Requires-Dist: pyyaml
Dynamic: license-file
